zircolite/.DS_Store
zircolite/__init__.py
zircolite/__main__.py
zircolite-2.9.15.dist-info/METADATA
zircolite-2.9.15.dist-info/WHEEL
zircolite-2.9.15.dist-info/entry_points.txt
zircolite-2.9.15.dist-info/RECORD
