Metadata-Version: 2.1
Name: zircolite
Version: 2.9.15
Summary: 
Author: wagga40
Author-email: 6437862+wagga40@users.noreply.github.com
Requires-Python: >=3.9,<4.0
Classifier: Programming Language :: Python :: 3
Classifier: Programming Language :: Python :: 3.9
Classifier: Programming Language :: Python :: 3.10
Classifier: Programming Language :: Python :: 3.11
Requires-Dist: aiohttp[speedups] (>=3.8.5,<4.0.0)
Requires-Dist: colorama (>=0.4.6,<0.5.0)
Requires-Dist: elasticsearch[async] (>=8.9.0,<9.0.0)
Requires-Dist: evtx (>=0.8.2,<0.9.0)
Requires-Dist: jinja2 (>=3.1.2,<4.0.0)
Requires-Dist: lxml (>=4.9.3,<5.0.0)
Requires-Dist: orjson (>=3.9.5,<4.0.0)
Requires-Dist: requests (>=2.31.0,<3.0.0)
Requires-Dist: tqdm (>=4.66.1,<5.0.0)
Requires-Dist: urllib3 (>=1.26.16,<2.0.0)
Requires-Dist: xxhash (>=3.3.0,<4.0.0)
